luau_tokenizer/__init__.py
luau_tokenizer/lexer.py
luau_tokenizer-1.1.1.dist-info/METADATA
luau_tokenizer-1.1.1.dist-info/WHEEL
luau_tokenizer-1.1.1.dist-info/top_level.txt
luau_tokenizer-1.1.1.dist-info/RECORD
