Metadata-Version: 2.1
Name: luau-tokenizer
Version: 1.1.1
Summary: Luau Tokenizer for LLM and Luau Code Analysis.
Home-page: https://pypi.org/project/luau-tokenizer/
Author: Mars
Author-email: hexgpcauthor@gmail.com
Classifier: Programming Language :: Python :: 3
Classifier: License :: OSI Approved :: MIT License
Classifier: Operating System :: OS Independent
Requires-Python: >=3.6
